{
	"kind" : "toolchains",
	"toolchains" : 
	[
		{
			"compiler" : 
			{
				"id" : "ARMClang",
				"implicit" : {},
				"path" : "c:/Users/Administrator/.vcpkg/artifacts/2da0b91a/compilers.arm.armclang/6.21.0/bin/armclang.exe",
				"target" : "arm-arm-none-eabi",
				"version" : ""
			},
			"language" : "ASM",
			"sourceFileExtensions" : 
			[
				"S",
				"s",
				"asm",
				"msa"
			]
		},
		{
			"compiler" : 
			{
				"id" : "ARMClang",
				"implicit" : 
				{
					"includeDirectories" : 
					[
						"C:/Users/Administrator/.vcpkg/artifacts/2da0b91a/compilers.arm.armclang/6.21.0/include"
					],
					"linkDirectories" : [],
					"linkFrameworkDirectories" : [],
					"linkLibraries" : []
				},
				"path" : "c:/Users/Administrator/.vcpkg/artifacts/2da0b91a/compilers.arm.armclang/6.21.0/bin/armclang.exe",
				"target" : "arm-arm-none-eabi",
				"version" : "6.21.0"
			},
			"language" : "C",
			"sourceFileExtensions" : 
			[
				"c",
				"m"
			]
		}
	],
	"version" : 
	{
		"major" : 1,
		"minor" : 0
	}
}
